MANIFEST.in
fastentrypoints.py
requirements.txt
setup.cfg
setup.py
libiocage/__init__.py
libiocage.egg-info/PKG-INFO
libiocage.egg-info/SOURCES.txt
libiocage.egg-info/dependency_links.txt
libiocage.egg-info/entry_points.txt
libiocage.egg-info/requires.txt
libiocage.egg-info/top_level.txt
libiocage/cli/__init__.py
libiocage/cli/activate.py
libiocage/cli/console.py
libiocage/cli/create.py
libiocage/cli/exec.py
libiocage/cli/fetch.py
libiocage/cli/get.py
libiocage/cli/list.py
libiocage/cli/set.py
libiocage/cli/start.py
libiocage/cli/stop.py
libiocage/lib/Datasets.py
libiocage/lib/Distribution.py
libiocage/lib/Host.py
libiocage/lib/Jail.py
libiocage/lib/JailConfig.py
libiocage/lib/JailConfigAddresses.py
libiocage/lib/JailConfigFstab.py
libiocage/lib/JailConfigInterfaces.py
libiocage/lib/JailConfigJSON.py
libiocage/lib/JailConfigLegacy.py
libiocage/lib/JailConfigResolver.py
libiocage/lib/JailConfigZFS.py
libiocage/lib/Jails.py
libiocage/lib/Logger.py
libiocage/lib/Network.py
libiocage/lib/NetworkInterface.py
libiocage/lib/NullFSBasejailStorage.py
libiocage/lib/Prompts.py
libiocage/lib/RCConf.py
libiocage/lib/Release.py
libiocage/lib/Releases.py
libiocage/lib/StandaloneJailStorage.py
libiocage/lib/Storage.py
libiocage/lib/ZFSBasejailStorage.py
libiocage/lib/ZFSShareStorage.py
libiocage/lib/__init__.py
libiocage/lib/errors.py
libiocage/lib/helpers.py
rc.d/ioc