Metadata-Version: 1.2
Name: libiocage
Version: 0.1.4
Summary: A Python library to manage jails with iocage
Home-page: https://github.com/iocage/libiocage
Author: Stefan Grönke, Brandon Schneider and Peter Toth
Author-email: stefan@gronke.net
License: BSD
Keywords: FreeBSD jail iocage
Platform: UNKNOWN
Requires-Python: >=3.6
